hyperon_das_atomdb/__init__.py
hyperon_das_atomdb/adapters/__init__.py
hyperon_das_atomdb/adapters/ram_only.py
hyperon_das_atomdb/adapters/redis_mongo_db.py
hyperon_das_atomdb/database.py
hyperon_das_atomdb/exceptions.py
hyperon_das_atomdb/index.py
hyperon_das_atomdb/logger.py
hyperon_das_atomdb/utils/expression_hasher.py
hyperon_das_atomdb/utils/settings.py
site-packages/__init__.py
site-packages/async_timeout-5.0.1.dist-info/INSTALLER
site-packages/async_timeout-5.0.1.dist-info/LICENSE
site-packages/async_timeout-5.0.1.dist-info/METADATA
site-packages/async_timeout-5.0.1.dist-info/WHEEL
site-packages/async_timeout-5.0.1.dist-info/top_level.txt
site-packages/async_timeout-5.0.1.dist-info/zip-safe
site-packages/async_timeout/__init__.py
site-packages/async_timeout/py.typed
site-packages/bson/__init__.py
site-packages/bson/_cbson.cpython-310-x86_64-linux-gnu.so
site-packages/bson/_cbsonmodule.c
site-packages/bson/_cbsonmodule.h
site-packages/bson/_helpers.py
site-packages/bson/binary.py
site-packages/bson/bson-endian.h
site-packages/bson/buffer.c
site-packages/bson/buffer.h
site-packages/bson/code.py
site-packages/bson/codec_options.py
site-packages/bson/datetime_ms.py
site-packages/bson/dbref.py
site-packages/bson/decimal128.py
site-packages/bson/errors.py
site-packages/bson/int64.py
site-packages/bson/json_util.py
site-packages/bson/max_key.py
site-packages/bson/min_key.py
site-packages/bson/objectid.py
site-packages/bson/py.typed
site-packages/bson/raw_bson.py
site-packages/bson/regex.py
site-packages/bson/son.py
site-packages/bson/time64.c
site-packages/bson/time64.h
site-packages/bson/time64_config.h
site-packages/bson/time64_limits.h
site-packages/bson/timestamp.py
site-packages/bson/typings.py
site-packages/bson/tz_util.py
site-packages/dns/__init__.py
site-packages/dns/_asyncbackend.py
site-packages/dns/_asyncio_backend.py
site-packages/dns/_ddr.py
site-packages/dns/_features.py
site-packages/dns/_immutable_ctx.py
site-packages/dns/_trio_backend.py
site-packages/dns/asyncbackend.py
site-packages/dns/asyncquery.py
site-packages/dns/asyncresolver.py
site-packages/dns/dnssec.py
site-packages/dns/dnssecalgs/__init__.py
site-packages/dns/dnssecalgs/base.py
site-packages/dns/dnssecalgs/cryptography.py
site-packages/dns/dnssecalgs/dsa.py
site-packages/dns/dnssecalgs/ecdsa.py
site-packages/dnspython-2.7.0.dist-info/INSTALLER
site-packages/dnspython-2.7.0.dist-info/METADATA
site-packages/dnspython-2.7.0.dist-info/WHEEL
site-packages/dnspython-2.7.0.dist-info/licenses/LICENSE
site-packages/hyperon_das_atomdb_cpp-0.0.2.dist-info/INSTALLER
site-packages/hyperon_das_atomdb_cpp-0.0.2.dist-info/METADATA
site-packages/hyperon_das_atomdb_cpp-0.0.2.dist-info/WHEEL
site-packages/pymongo-4.5.0.dist-info/INSTALLER
site-packages/pymongo-4.5.0.dist-info/LICENSE
site-packages/pymongo-4.5.0.dist-info/METADATA
site-packages/pymongo-4.5.0.dist-info/WHEEL
site-packages/pymongo-4.5.0.dist-info/top_level.txt
site-packages/python_dotenv-1.0.1.dist-info/INSTALLER
site-packages/python_dotenv-1.0.1.dist-info/LICENSE
site-packages/python_dotenv-1.0.1.dist-info/METADATA
site-packages/python_dotenv-1.0.1.dist-info/WHEEL
site-packages/python_dotenv-1.0.1.dist-info/entry_points.txt
site-packages/python_dotenv-1.0.1.dist-info/top_level.txt
site-packages/redis-5.2.1.dist-info/INSTALLER
site-packages/redis-5.2.1.dist-info/LICENSE
site-packages/redis-5.2.1.dist-info/METADATA
site-packages/redis-5.2.1.dist-info/WHEEL
site-packages/redis-5.2.1.dist-info/top_level.txt
hyperon_das_atomdb-0.10.1.dist-info/WHEEL
hyperon_das_atomdb-0.10.1.dist-info/METADATA
hyperon_das_atomdb-0.10.1.dist-info/RECORD
