Metadata-Version: 2.1
Name: hyperon_das_atomdb
Author: Andre Senna
Author-email: andre@singularitynet.io
Summary: Persistence layer for Distributed AtomSpace
Classifier: Programming Language :: Python :: 3
Classifier: Programming Language :: Python :: 3.10
Classifier: Programming Language :: Python :: 3.11
Classifier: Programming Language :: Python :: 3.12
Classifier: Programming Language :: Python :: 3.13
Requires-Python: >=3.10
Requires-Dist: async-timeout==5.0.1
Requires-Dist: dnspython==2.7.0
Requires-Dist: hyperon-das-atomdb-cpp==0.0.2
Requires-Dist: pymongo==4.5.0
Requires-Dist: python-dotenv==1.0.1
Requires-Dist: redis==5.2.1
Version: 0.10.1
